scitbx/__init__.py
scitbx/commons.py
scitbx/easy_import.py
scitbx/files.py
scitbx/google.py
scitbx/sciplt.py
scitbx/utils.py
scitbx-0.0.94.dist-info/METADATA
scitbx-0.0.94.dist-info/WHEEL
scitbx-0.0.94.dist-info/top_level.txt
scitbx-0.0.94.dist-info/RECORD
