Metadata-Version: 2.1
Name: scitbx
Version: 0.0.94
Summary: For academic data processing and plotting etc.
Home-page: https://github.com/soonyenju/scitbx
Author: Songyan Zhu
Author-email: zhusy93@gmail.com
License: MIT Licence
Keywords: Geosciences,geospatial,data science
Platform: any
